pynumato/__init__.py
pynumato/pynumato.py
pynumato-0.0.1.dist-info/METADATA
pynumato-0.0.1.dist-info/WHEEL
pynumato-0.0.1.dist-info/top_level.txt
pynumato-0.0.1.dist-info/RECORD
