Metadata-Version: 2.1
Name: pynumato
Version: 0.0.1
Summary: Library to communicate with relays
Home-page: https://github.com/henitsoa-tiempo/pynumato.git
Author: Tiempo
Author-email: henitsoa.rakotomalala@tiempo-secure.com
License: UNKNOWN
Platform: UNKNOWN
Classifier: Programming Language :: Python :: 3
Classifier: Operating System :: OS Independent
